tgtools/__init__.py
tgtools/consts.py
tgtools/tgcrawl.py
tgtools/crawler/__init__.py
tgtools/crawler/batch.py
tgtools/crawler/commander.py
tgtools/drivers/__init__.py
tgtools/drivers/sshnetconf.py
tgtools/parsers/__init__.py
tgtools/parsers/events/__init__.py
tgtools/parsers/events/event.py
tgtools/parsers/events/events.py
tgtools/parsers/status/__init__.py
tgtools/parsers/status/tgparser.py
tgtools/parsers/techlog/__init__.py
tgtools/parsers/techlog/techlog.py
tgtools/utils/__init__.py
tgtools/utils/cmdlog.py
tgtools/utils/credentials.py
tgtools/utils/errlog.py
tgtools/utils/miscfuncs.py
tgtools/utils/mylogger.py
tgtools/utils/timefunc.py
tgtools/utils/xlookup.py
tgtools/utils/ioutils/__init__.py
tgtools/utils/ioutils/iocsv.py
tgtools/utils/ioutils/iogen.py
mh_tgtools-0.3.2.dist-info/METADATA
mh_tgtools-0.3.2.dist-info/WHEEL
mh_tgtools-0.3.2.dist-info/entry_points.txt
mh_tgtools-0.3.2.dist-info/top_level.txt
mh_tgtools-0.3.2.dist-info/RECORD
