Metadata-Version: 2.2
Name: mh-tgtools
Version: 0.3.2
Summary: A collection of tools to manage Ceragon by Siklu MultiHaul TG radios
Author-email: Daniel Ephraty <daniel@ephraty.com>
Project-URL: repository, https://github.com/DanielEphraty/tgtools
Project-URL: documentation, https://tgtools.readthedocs.io/en/latest/
Keywords: TG,batch,siklu,siklu radios,scanner,MultiHaul
Classifier: License :: OSI Approved :: MIT License
Classifier: Programming Language :: Python
Classifier: Programming Language :: Python :: 3
Requires-Python: >=3.13
Requires-Dist: ncclient
Requires-Dist: lxml
Provides-Extra: build
Requires-Dist: build; extra == "build"
Requires-Dist: twine; extra == "build"
Provides-Extra: dev
Requires-Dist: sphinx-rtd-theme; extra == "dev"
